mediaquery/__init__.py
mediaquery/mediaquery.py
mediaquery/lib/Argument.py
mediaquery/lib/__init__.py
mediaquery-0.1.6.dist-info/METADATA
mediaquery-0.1.6.dist-info/WHEEL
mediaquery-0.1.6.dist-info/entry_points.txt
mediaquery-0.1.6.dist-info/top_level.txt
mediaquery-0.1.6.dist-info/RECORD
