Metadata-Version: 2.1
Name: mediaquery
Version: 0.1.6
Summary: MediaQuery is a wrapper for mediainfo tool
Home-page: https://git.selfmade.ninja/sibidharan/mediaquery-with-mediainfo
Author: Sibidharan
Author-email: sibi@selfmade.ninja
License: UNKNOWN
Platform: UNKNOWN
Requires-Dist: pymongo (==3.11.0)
